{
  "Trade": {
    "name": "Trade",
    "activities": [
      "Trade Initiated",
      "Trade Execution",
      "Trade Validation",
      "Trade Confirmation",
      "Trade Matching",
      "Trade Reconciliation",
      "Final Settlement",
      "Trade Transparency Assessment"
    ],
    "attributes": [
      "booking_system",
      "case_id",
      "client_type",
      "currency_pair",
      "notional_amount",
      "option_type",
      "premium",
      "strike_price",
      "trading_strategy"
    ],
    "relationships": [
      "Client",
      "MarketData",
      "Order",
      "Position"
    ]
  },
  "Order": {
    "name": "Order",
    "activities": [
      "Quote Requested",
      "Quote Provided",
      "Client Limit Validation",
      "Strategy Validation",
      "ISDA Master Agreement Check",
      "KYC Refresh Check",
      "Best Execution Validation",
      "Exercise Decision",
      "Trade Allocation"
    ],
    "attributes": [
      "booking_system",
      "case_id",
      "client_type",
      "currency_pair",
      "option_type",
      "trading_strategy"
    ],
    "relationships": [
      "Client",
      "MarketData",
      "Trade"
    ]
  },
  "Position": {
    "name": "Position",
    "activities": [
      "Position Reconciliation",
      "Risk Assessment",
      "Initial Margin Calculation",
      "Collateral Management"
    ],
    "attributes": [
      "booking_system",
      "case_id",
      "client_type",
      "currency_pair",
      "limit_usage",
      "option_type",
      "risk_score",
      "trading_strategy"
    ],
    "relationships": [
      "Client",
      "Trade"
    ]
  },
  "MarketData": {
    "name": "MarketData",
    "activities": [
      "Market Data Validation",
      "Volatility Surface Analysis",
      "Greeks Calculation",
      "Premium Calculation",
      "CSA Verification",
      "Transaction Reporting Check",
      "Regulatory Reporting Generation"
    ],
    "attributes": [
      "booking_system",
      "case_id",
      "client_type",
      "currency_pair",
      "delta",
      "gamma",
      "option_type",
      "theta",
      "trading_strategy",
      "vega"
    ],
    "relationships": [
      "Order",
      "Trade"
    ]
  },
  "Client": {
    "name": "Client",
    "activities": [
      "Credit Check",
      "Settlement Instructions",
      "Premium Settlement"
    ],
    "attributes": [
      "booking_system",
      "case_id",
      "client_type",
      "currency_pair",
      "trading_strategy"
    ],
    "relationships": [
      "Order",
      "Position",
      "Trade"
    ]
  }
}